pidoorbuzz/__init__.py
pidoorbuzz/_listener.py
pidoorbuzz/_processor.py
pidoorbuzz/_settings.py
pi_door_buzz-0.2.dist-info/LICENSE
pi_door_buzz-0.2.dist-info/METADATA
pi_door_buzz-0.2.dist-info/WHEEL
pi_door_buzz-0.2.dist-info/top_level.txt
pi_door_buzz-0.2.dist-info/RECORD
