Metadata-Version: 2.1
Name: pi-door-buzz
Version: 0.2
Summary: A python package for door buzz detection
Home-page: https://github.com/yechoorv/pi-door-buzz
Download-URL: https://github.com/yechoorv/pi-door-buzz
Author: Vamsi Yechoor
Author-email: yechoorv@gmail.com
License: MIT
Platform: any
Classifier: Intended Audience :: Developers
Classifier: Environment :: Console
Classifier: Operating System :: OS Independent
Classifier: Programming Language :: Python
Classifier: Programming Language :: Python :: 3.6
Classifier: Programming Language :: Python :: 3.7
Classifier: Programming Language :: Python :: 3.8
Classifier: Topic :: Software Development
Classifier: Topic :: Software Development :: Libraries
Classifier: Topic :: Utilities
Classifier: License :: OSI Approved :: MIT License
Requires-Python: >=3.6
License-File: LICENSE
Requires-Dist: gpiozero (==1.5.1)
Requires-Dist: pyaudio (==0.2.11)
Requires-Dist: munch (==2.5.0)
